{
  "ColorChip": {
    "pages": 1,
    "colorsPerPage": 64,
    "supportedColors": 16,
    "backgroundColor": 0,
    "transparent": "#FF00FF"
  },
  "DisplayChip": {
    "width": 128,
    "height": 128,
    "overscanX": 0,
    "overscanY": 0,
    "layers": 6

  },
  "ControllerChip": {},
  "FontChip": {},
  "GameChip": {
    "name": "SpirallySpiralDemo",
    "description": "",
    "version": "0.8.0",
    "ext": ".pv8",
    "lockSpecs": true,
    "maxSize": 64,
    "saveSlots": 8
  },
  "MusicChip": {
    "totalTracks": 4,
    "notesPerTrack": 127,
    "totalLoop": 32
  },
  "SoundChip": {
    "totalChannels": 5,
    "totalSounds": 32
  },

  "SpriteChip": {
    "maxSpriteCount": 0,
    "unique": false,
    "spriteWidth": 8,
    "spriteHeight": 8,
    "pages": 1,
    "cps": 16
  },
  "TilemapChip": {
    "columns": 128,
    "rows": 64,
    "totalFlags": 16
  }
}